toolrack/__init__.py
toolrack/certificate.py
toolrack/collect.py
toolrack/config.py
toolrack/convert.py
toolrack/fsmap.py
toolrack/iterate.py
toolrack/json_util.py
toolrack/log.py
toolrack/password.py
toolrack/path.py
toolrack/property.py
toolrack/py.typed
toolrack/script.py
toolrack/threading.py
toolrack/aio/__init__.py
toolrack/aio/periodic.py
toolrack/aio/process.py
toolrack/scripts/__init__.py
toolrack/scripts/certinfo.py
toolrack/scripts/password_generator.py
toolrack/testing/__init__.py
toolrack/testing/fixtures.py
toolrack/testing/tests/__init__.py
toolrack-4.0.1.dist-info/LICENSE.txt
toolrack-4.0.1.dist-info/METADATA
toolrack-4.0.1.dist-info/WHEEL
toolrack-4.0.1.dist-info/entry_points.txt
toolrack-4.0.1.dist-info/top_level.txt
toolrack-4.0.1.dist-info/RECORD
