Metadata-Version: 2.1
Name: toolrack
Version: 4.0.1
Summary: A collection of miscellaneous utility functions and classes
Author-email: Alberto Donato <alberto.donato@gmail.com>
Maintainer-email: Alberto Donato <alberto.donato@gmail.com>
License: GNU LESSER GENERAL PUBLIC LICENSE
Project-URL: changelog, https://github.com/albertodonato/toolrack/blob/main/CHANGES.rst
Project-URL: documentation, https://readthedocs.org/projects/toolrack/
Project-URL: homepage, https://github.com/albertodonato/toolrack
Project-URL: repository, https://github.com/albertodonato/toolrack
Keywords: asyncio,library,utility
Classifier: Development Status :: 5 - Production/Stable
Classifier: Intended Audience :: Developers
Classifier: Intended Audience :: System Administrators
Classifier: License :: OSI Approved :: GNU Lesser General Public License v3 or later (LGPLv3+)
Classifier: Operating System :: OS Independent
Classifier: Programming Language :: Python :: 3 :: Only
Classifier: Programming Language :: Python :: 3.10
Classifier: Programming Language :: Python :: 3.11
Classifier: Programming Language :: Python :: 3.12
Classifier: Programming Language :: Python :: 3.13
Classifier: Topic :: Software Development :: Libraries
Classifier: Topic :: Software Development :: Libraries :: Python Modules
Classifier: Topic :: Utilities
Requires-Python: >=3.10
License-File: LICENSE.txt
Requires-Dist: pytest
Provides-Extra: testing
Requires-Dist: pytest-asyncio ; extra == 'testing'
Requires-Dist: pytest-mock ; extra == 'testing'
